{"id":"20202","name":"Reed Pipe","transitionsToward":[{"targetID":"20203","newActorID":"20202","newTargetID":"124","hand":true},{"targetID":"20206","newActorID":"20202","newTargetID":"20418","hand":true},{"targetID":"20414","newActorID":"20202","newTargetID":"20418","hand":true},{"targetID":"20423","newActorID":"20202","newTargetID":"20416","hand":true},{"targetID":"20204","newActorID":"20202","newTargetID":"20416","hand":true}],"transitionsAway":[{"actorID":"20202","targetID":"299","newTargetID":"20414"},{"actorID":"20202","targetID":"20417","newTargetID":"20414"},{"actorID":"20202","targetID":"20418","newTargetID":"20414"},{"actorID":"20202","targetID":"238","newTargetID":"20204"},{"actorID":"20202","targetID":"20415","newTargetID":"20204"},{"actorID":"20202","targetID":"20416","newTargetID":"20204"},{"actorID":"20202","targetID":"617","newTargetUses":"-1","newTargetID":"617","targetRemains":true},{"actorID":"20202","targetID":"617","targetUses":"last","newTargetID":"618"},{"actorID":"20202","targetID":"620","newTargetUses":"-1","newTargetID":"620","targetRemains":true},{"actorID":"20202","targetID":"620","targetUses":"last","newTargetID":"621"}],"techTree":[{"id":"20203","nodes":[{"id":"135","nodes":[{"id":"150","nodes":[]}]},{"id":"124","nodes":[{"id":"123","nodes":[]}]}]}]}