{"id":"20383","name":"Copper File Blank","transitionsToward":[{"actorID":"33","targetID":"20269","newActorID":"33","newTargetID":"20383","tool":true},{"actorID":"20030","targetID":"20269","newActorID":"20030","newTargetID":"20383","tool":true},{"targetID":"20359","newActorID":"20383","newTargetID":"20287","hand":true},{"actorID":"20127","targetID":"20269","newActorID":"20127","newTargetID":"20383","tool":true}],"transitionsAway":[{"actorID":"518","targetID":"20383","newActorID":"518","newTargetID":"20433","tool":true}],"complexity":239,"techTree":[{"id":"33","nodes":null},{"id":"20269","nodes":[{"decay":"10s"},{"id":"20242","nodes":[{"id":"20010","nodes":[]},{"id":"20232","nodes":[]}]}]}]}