{"id":"20541","name":"Tin Anvil","transitionsToward":[{"targetID":"20540","newActorID":"20541","newTargetID":"20461","hand":true,"decay":"10s"}],"transitionsAway":[{"actorID":"441","targetID":"20541","newActorID":"441","newTargetID":"20555","tool":true},{"actorID":"20030","targetID":"20541","newActorID":"20030","newTargetID":"20555","tool":true},{"actorID":"20127","targetID":"20541","newActorID":"20127","newTargetID":"20555","tool":true},{"actorID":"20627","targetID":"20541","newActorID":"20627","newTargetID":"20555","tool":true},{"actorID":"20613","targetID":"20541","newActorID":"20613","newTargetID":"20555","tool":true},{"actorID":"20541","newTargetID":"20555"}],"transitionsTimed":[],"techTree":[{"decay":"10s"},{"id":"20540","nodes":[{"decay":"10s"},{"id":"20539","nodes":[{"decay":"10s"},{"id":"20534","nodes":[]}]}]}]}