{"id":"465","name":"Oiled File Blank with Chisel","transitionsToward":[{"actorID":"455","targetID":"464","newTargetID":"465"}],"transitionsAway":[{"targetID":"465","newActorID":"455","newTargetID":"464","hand":true},{"actorID":"441","targetID":"465","newActorID":"441","newTargetID":"466","tool":true},{"actorID":"20030","targetID":"465","newActorID":"20030","newTargetID":"466","tool":true},{"actorID":"20127","targetID":"465","newActorID":"20127","newTargetID":"466","tool":true},{"actorID":"20627","targetID":"465","newActorID":"20627","newTargetID":"466","tool":true},{"actorID":"20613","targetID":"465","newActorID":"20613","newTargetID":"466","tool":true}],"version":36,"techTree":[{"id":"455","nodes":[{"id":"20781","nodes":[{"id":"20665","nodes":[]},{"id":"504","nodes":[]}]}]},{"id":"464","nodes":[{"id":"465","nodes":[{"id":"455","nodes":[]},{"id":"464","nodes":[]}]}]}]}