{"id":"597","name":"Dead Sheep - shorn","transitionsToward":[{"targetID":"598","newActorID":"578","newTargetID":"597","hand":true},{"actorID":"135","targetID":"576","newActorID":"135","newTargetID":"597","tool":true},{"actorID":"20047","targetID":"576","newActorID":"20047","newTargetID":"597","tool":true},{"actorID":"20182","targetID":"576","newActorID":"20182","newTargetID":"597","tool":true},{"actorID":"560","targetID":"576","newActorID":"560","newTargetID":"597","tool":true}],"transitionsAway":[{"actorID":"135","targetID":"597","newActorID":"135","newTargetID":"587","tool":true},{"actorID":"20047","targetID":"597","newActorID":"20047","newTargetID":"587","tool":true},{"actorID":"20182","targetID":"597","newActorID":"20182","newTargetID":"587","tool":true},{"actorID":"560","targetID":"597","newActorID":"560","newTargetID":"587","tool":true}],"version":52,"complexity":428,"techTree":[{"id":"598","nodes":[{"id":"20052","nodes":[{"id":"135","nodes":[]},{"id":"20070","nodes":[]}]},{"id":"595","nodes":[{"id":"135","nodes":[]},{"id":"575","nodes":[]}]}]}]}